xyconvert.py
xyconvert-0.1.2.dist-info/METADATA
xyconvert-0.1.2.dist-info/RECORD
xyconvert-0.1.2.dist-info/WHEEL
xyconvert-0.1.2.dist-info/top_level.txt
