Metadata-Version: 2.1
Name: xyconvert
Version: 0.1.2
Summary: Convert xy coordinates
Home-page: https://github.com/cyang-kth/xyconvert
Author: Can Yang
Author-email: ycycy1990@hotmail.com
License: MIT
Platform: UNKNOWN
Requires-Dist: numpy
Requires-Dist: pyproj
